bgls/__init__.py
bgls/_version.py
bgls/apply.py
bgls/apply_test.py
bgls/born.py
bgls/born_test.py
bgls/near_clifford_solver.py
bgls/near_clifford_solver_test.py
bgls/optimize.py
bgls/optimize_test.py
bgls/simulator.py
bgls/simulator_test.py
bgls/testing.py
bgls/testing_test.py
bgls-0.2.0.dist-info/LICENSE
bgls-0.2.0.dist-info/METADATA
bgls-0.2.0.dist-info/WHEEL
bgls-0.2.0.dist-info/top_level.txt
bgls-0.2.0.dist-info/RECORD
