Metadata-Version: 2.1
Name: bgls
Version: 0.2.0
Summary: Implementation of the gate-by-gate sampling algorithm.
Home-page: https://github.com/asciineuron/bgls
Author: Alex Shapiro
Author-email: alexander.shapiro@epfl.ch
License: Apache 2.0
Project-URL: Bug Tracker, https://github.com/asciineuron/bgls/issues/
Project-URL: Documentation, https://github.com/asciineuron/bgls
Project-URL: Source, https://github.com/asciineuron/bgls
Requires-Python: >=3.9.0
License-File: LICENSE
Requires-Dist: cirq-core >=1.1.0
Provides-Extra: development
Requires-Dist: pytest-xdist[psutil] ; extra == 'development'
Requires-Dist: quimb[tensor] ; extra == 'development'
Requires-Dist: black ; extra == 'development'
Requires-Dist: sphinx ; extra == 'development'
Requires-Dist: nbmake ; extra == 'development'
Requires-Dist: ply ; extra == 'development'
Requires-Dist: quimb ; extra == 'development'
Requires-Dist: furo ; extra == 'development'
Requires-Dist: pytest-cov ; extra == 'development'
Requires-Dist: myst-nb ; extra == 'development'
Requires-Dist: flake8 ; extra == 'development'
Requires-Dist: mypy ; extra == 'development'
